setup.py
doctorwho/__init__.py
doctorwho.egg-info/PKG-INFO
doctorwho.egg-info/SOURCES.txt
doctorwho.egg-info/dependency_links.txt
doctorwho.egg-info/top_level.txt