Metadata-Version: 1.0
Name: doctorwho
Version: 0.0.1
Summary: Some funny app!
Home-page: https://github.com/tongxiaoting
Author: Tong
Author-email: 3168095199@qq.com
License: UNKNOWN
Platform: UNKNOWN
